{"trial_id": "2", "hyperparameters": {"space": [{"class_name": "Int", "config": {"name": "units1", "default": null, "conditions": [], "min_value": 32, "max_value": 128, "step": 32, "sampling": "linear"}}, {"class_name": "Int", "config": {"name": "units2", "default": null, "conditions": [], "min_value": 32, "max_value": 128, "step": 32, "sampling": "linear"}}, {"class_name": "Choice", "config": {"name": "learning_rate", "default": 0.01, "conditions": [], "values": [0.01, 0.001, 0.0001], "ordered": true}}], "values": {"units1": 96, "units2": 128, "learning_rate": 0.001}}, "metrics": {"metrics": {"loss": {"direction": "min", "observations": [{"value": [0.683893084526062], "step": 6}]}, "accuracy": {"direction": "max", "observations": [{"value": [0.553113579750061], "step": 6}]}, "val_loss": {"direction": "min", "observations": [{"value": [0.6858651041984558], "step": 6}]}, "val_accuracy": {"direction": "max", "observations": [{"value": [0.5541601181030273], "step": 6}]}}}, "score": 0.5541601181030273, "best_step": 6, "status": "COMPLETED", "message": null}